<?xml version="1.0" encoding="UTF-8"?>
<odoo>
    <!--add snippet options-->
    <template id="snippet_footer_redeem" inherit_id="website.snippet_options_conditional_visibility">
        <xpath expr="//div/we-select[@data-variable='footer-template']" position="inside">
            <we-button title="Custom Footer" data-name="footer_custom_opt"
                       data-customize-website-views="theme_redeem.custom_theme_redeem_footer"
                       data-customize-website-variable="'custom_footer'"
                       data-img="/website/static/src/img/snippets_options/footer_template_contact.svg"/>
        </xpath>
    </template>
    <template
            id="custom_theme_redeem_footer"
            inherit_id="website.layout"
            name="Redeem Footer"
    >
        <xpath expr="//footer" position="replace">
            <footer class="pt-5 bg-primary text-white">
                <div class="container py-lg-3">
                    <div class="d-flex justify-content-between   align-items-center flex-wrap">
                        <a href="" class="logo m-auto m-lg-0 ">
                            <svg width="118" height="38" viewBox="0 0 118 38" fill="none"
                                 xmlns="http://www.w3.org/2000/svg">
                                <path d="M6.04199 27.9832V12.1039H11.5093V14.3956H11.5683C11.6101 14.3143 11.6777 14.2108 11.7699 14.0851C11.8609 13.9607 12.0612 13.7438 12.3697 13.4346C12.6807 13.1265 13.0101 12.8481 13.358 12.6017C13.7083 12.3528 14.1606 12.131 14.715 11.9363C15.2718 11.7392 15.8385 11.6406 16.4162 11.6406C17.0123 11.6406 17.5986 11.7232 18.1763 11.887C18.7528 12.0521 19.1756 12.216 19.4448 12.3799L19.8775 12.6312L17.5912 17.2738C16.9127 16.6959 15.9651 16.4064 14.7494 16.4064C14.0906 16.4064 13.5227 16.5518 13.0482 16.8401C12.5762 17.1296 12.2419 17.4808 12.0452 17.8948C11.851 18.3063 11.7134 18.6562 11.6322 18.9445C11.5499 19.2341 11.5093 19.4608 11.5093 19.6246V27.9832H6.04199Z"
                                      fill="white"/>
                                <path d="M34.8233 20.8025H23.3331C23.3331 21.9163 23.6932 22.7431 24.4147 23.2815C25.135 23.8175 25.9168 24.0848 26.76 24.0848C27.645 24.0848 28.3444 23.9666 28.8594 23.73C29.3732 23.491 29.9607 23.0203 30.6196 22.3205L34.5726 24.3017C32.9267 27.0653 30.1894 28.4465 26.3617 28.4465C23.9722 28.4465 21.922 27.6271 20.211 25.9872C18.5025 24.3485 17.6494 22.3735 17.6494 20.0633C17.6494 17.7506 18.5025 15.7694 20.211 14.1196C21.922 12.4674 23.9722 11.6406 26.3617 11.6406C28.8717 11.6406 30.9146 12.3688 32.4879 13.8239C34.0637 15.2766 34.8528 17.3551 34.8528 20.0583C34.8528 20.4304 34.843 20.6781 34.8233 20.8025ZM23.4904 17.7666H29.5084C29.3867 16.9424 29.0622 16.3078 28.5349 15.8643C28.0101 15.4207 27.3365 15.1989 26.5142 15.1989C25.6095 15.1989 24.888 15.438 24.3508 15.9136C23.8161 16.3867 23.5297 17.0052 23.4904 17.7666Z"
                                      fill="white"/>
                                <path d="M35.8659 26.0168C34.3835 24.3978 33.6436 22.4117 33.6436 20.0583C33.6436 17.7063 34.3835 15.7152 35.8659 14.0851C37.3507 12.4563 39.235 11.6406 41.5201 11.6406C43.6207 11.6406 45.3501 12.301 46.7071 13.6219V1.35999H52.1745V27.9832H46.7711V26.1893H46.7071C45.3501 27.6949 43.6207 28.4465 41.5201 28.4465C39.235 28.4465 37.3507 27.637 35.8659 26.0168ZM40.5171 17.3674C39.8054 18.0673 39.4501 18.9642 39.4501 20.0583C39.4501 21.1525 39.7894 22.047 40.4679 22.7394C41.1488 23.4294 42.0461 23.7744 43.1573 23.7744C44.2291 23.7744 45.1092 23.4244 45.7976 22.7246C46.4859 22.0223 46.8301 21.1327 46.8301 20.0583C46.8301 18.9642 46.4736 18.0673 45.7631 17.3674C45.0551 16.6651 44.1861 16.3128 43.1573 16.3128C42.1076 16.3128 41.2275 16.6651 40.5171 17.3674Z"
                                      fill="white"/>
                                <path d="M69.2833 20.8025H57.793C57.793 21.9163 58.1532 22.7431 58.8747 23.2815C59.595 23.8175 60.3767 24.0848 61.22 24.0848C62.105 24.0848 62.8044 23.9666 63.3194 23.73C63.8332 23.491 64.4207 23.0203 65.0795 22.3205L69.0325 24.3017C67.3867 27.0653 64.6493 28.4465 60.8217 28.4465C58.4322 28.4465 56.382 27.6271 54.671 25.9872C52.9624 24.3485 52.1094 22.3735 52.1094 20.0633C52.1094 17.7506 52.9624 15.7694 54.671 14.1196C56.382 12.4674 58.4322 11.6406 60.8217 11.6406C63.3317 11.6406 65.3745 12.3688 66.9479 13.8239C68.5237 15.2766 69.3128 17.3551 69.3128 20.0583C69.3128 20.4304 69.303 20.6781 69.2833 20.8025ZM57.9504 17.7666H63.9684C63.8467 16.9424 63.5222 16.3078 62.9949 15.8643C62.47 15.4207 61.7964 15.1989 60.9741 15.1989C60.0695 15.1989 59.3479 15.438 58.8108 15.9136C58.2761 16.3867 57.9897 17.0052 57.9504 17.7666Z"
                                      fill="white"/>
                                <path d="M85.2784 20.8025H73.7882C73.7882 21.9163 74.1483 22.7431 74.8698 23.2815C75.5901 23.8175 76.3719 24.0848 77.2151 24.0848C78.1001 24.0848 78.7995 23.9666 79.3145 23.73C79.8283 23.491 80.4158 23.0203 81.0747 22.3205L85.0277 24.3017C83.3818 27.0653 80.6445 28.4465 76.8168 28.4465C74.4273 28.4465 72.3771 27.6271 70.6661 25.9872C68.9575 24.3485 68.1045 22.3735 68.1045 20.0633C68.1045 17.7506 68.9575 15.7694 70.6661 14.1196C72.3771 12.4674 74.4273 11.6406 76.8168 11.6406C79.3268 11.6406 81.3697 12.3688 82.943 13.8239C84.5188 15.2766 85.3079 17.3551 85.3079 20.0583C85.3079 20.4304 85.2981 20.6781 85.2784 20.8025ZM73.9455 17.7666H79.9635C79.8418 16.9424 79.5173 16.3078 78.99 15.8643C78.4651 15.4207 77.7916 15.1989 76.9692 15.1989C76.0646 15.1989 75.3431 15.438 74.8059 15.9136C74.2712 16.3867 73.9848 17.0052 73.9455 17.7666Z"
                                      fill="white"/>
                                <path d="M85.2451 27.9832V12.1039H90.7125V13.7746H90.7715C92.1936 12.3528 93.7067 11.6406 95.3095 11.6406C96.4625 11.6406 97.5442 11.8797 98.5545 12.3552C99.5637 12.8284 100.326 13.5602 100.841 14.5484C102.446 12.6103 104.196 11.6406 106.092 11.6406C107.779 11.6406 109.23 12.1162 110.443 13.0649C111.659 14.0112 112.267 15.4971 112.267 17.5202V27.9832H106.8V19.0086C106.8 18.1609 106.566 17.4549 106.102 16.8894C105.639 16.3214 104.946 16.0368 104.022 16.0368C103.218 16.0368 102.606 16.2807 102.183 16.7662C101.76 17.2491 101.529 17.8307 101.49 18.5108V27.9832H96.0225V19.0086C96.0225 18.1609 95.7889 17.4549 95.3243 16.8894C94.8621 16.3214 94.1689 16.0368 93.2445 16.0368C92.3989 16.0368 91.7646 16.3004 91.3418 16.8253C90.9214 17.3514 90.7125 17.9761 90.7125 18.6981V27.9832H85.2451Z"
                                      fill="white"/>
                            </svg>
                        </a>
                        <ul class="list-unstyled mt-2 w-100 w-lg-auto     text-white pt-3 m-auto m-lg-0  d-flex justify-content-center align-items-center  gap-5">
                            <li>
                                <a class="text-white pt-2 pt-lg-0 d-inline-block " href="/">Home</a>
                            </li>
                            <li>
                                <a href="/#features" class="text-white pt-2 pt-lg-0 d-inline-block ">Features</a>
                            </li>
                            <li>
                                <a href="/#how-it-works" class="text-white pt-2 pt-lg-0 d-inline-block ">How It Works
                                </a>
                            </li>
                        </ul>
                    </div>
                    <p class="coopy-write text-center text-white mt-lg-5 mt-3 pt-3">Copyright © 2025 Taqat</p>
                </div>
            </footer>
        </xpath>
    </template>
</odoo>
